howistheweathertoday
