Metadata-Version: 2.1
Name: howistheweathertoday
Version: 1.1.0
Summary: Weather forecast data
Author: Mehmet Ali Soylu
Author-email: mhmtsoylu1928@gmail.com
License: MIT
Keywords: weather,forecast,openweather
